sampleArthmeticFunction/__init__.py
sampleArthmeticFunction/arthmetic.py
sampleArthmeticFunction-0.0.2.dist-info/METADATA
sampleArthmeticFunction-0.0.2.dist-info/WHEEL
sampleArthmeticFunction-0.0.2.dist-info/top_level.txt
sampleArthmeticFunction-0.0.2.dist-info/RECORD
